gudhi/__init__.py
gudhi/_edge_collapse.cp313-win_amd64.pyd
gudhi/_kepler_mapper.py
gudhi/_pers_cub_low_dim.cp313-win_amd64.pyd
gudhi/_ripser.cp313-win_amd64.pyd
gudhi/bottleneck.cp313-win_amd64.pyd
gudhi/cover_complex.py
gudhi/cubical_complex.cp313-win_amd64.pyd
gudhi/delaunay_complex.cp313-win_amd64.pyd
gudhi/dtm_rips_complex.py
gudhi/euclidean_strong_witness_complex.cp313-win_amd64.pyd
gudhi/euclidean_witness_complex.cp313-win_amd64.pyd
gudhi/gmp-10.dll
gudhi/gmpxx-4.dll
gudhi/mpfr-6.dll
gudhi/nerve_gic.cp313-win_amd64.pyd
gudhi/off_utils.cp313-win_amd64.pyd
gudhi/periodic_cubical_complex.cp313-win_amd64.pyd
gudhi/persistence_graphical_tools.py
gudhi/reader_utils.cp313-win_amd64.pyd
gudhi/rips_complex.cp313-win_amd64.pyd
gudhi/simplex_tree.cp313-win_amd64.pyd
gudhi/strong_witness_complex.cp313-win_amd64.pyd
gudhi/subsampling.cp313-win_amd64.pyd
gudhi/tangential_complex.cp313-win_amd64.pyd
gudhi/weighted_rips_complex.py
gudhi/witness_complex.cp313-win_amd64.pyd
gudhi/clustering/__init__.py
gudhi/clustering/_tomato.cp313-win_amd64.pyd
gudhi/clustering/tomato.py
gudhi/datasets/__init__.py
gudhi/datasets/remote.py
gudhi/datasets/generators/__init__.py
gudhi/datasets/generators/_points.cp313-win_amd64.pyd
gudhi/datasets/generators/points.py
gudhi/flag_filtration/__init__.py
gudhi/flag_filtration/edge_collapse.py
gudhi/hera/__init__.py
gudhi/hera/bottleneck.cp313-win_amd64.pyd
gudhi/hera/wasserstein.cp313-win_amd64.pyd
gudhi/point_cloud/__init__.py
gudhi/point_cloud/dtm.py
gudhi/point_cloud/knn.py
gudhi/point_cloud/timedelay.py
gudhi/representations/__init__.py
gudhi/representations/kernel_methods.py
gudhi/representations/metrics.py
gudhi/representations/preprocessing.py
gudhi/representations/vector_methods.py
gudhi/sklearn/__init__.py
gudhi/sklearn/cubical_persistence.py
gudhi/sklearn/rips_persistence.py
gudhi/tensorflow/__init__.py
gudhi/tensorflow/cubical_layer.py
gudhi/tensorflow/lower_star_simplex_tree_layer.py
gudhi/tensorflow/perslay.py
gudhi-3.11.0.dist-info/METADATA
gudhi-3.11.0.dist-info/WHEEL
gudhi-3.11.0.dist-info/top_level.txt
gudhi-3.11.0.dist-info/RECORD
