Metadata-Version: 2.1
Name: gudhi
Version: 3.11.0
Summary: The Gudhi library is an open source library for Computational Topology and Topological Data Analysis (TDA).
Home-page: https://gudhi.inria.fr/
Author: GUDHI Editorial Board <https://gudhi.inria.fr/contact/>
License: UNKNOWN
Project-URL: Bug Tracker, https://github.com/GUDHI/gudhi-devel/issues
Project-URL: Documentation, https://gudhi.inria.fr/python/latest/
Project-URL: Source Code, https://github.com/GUDHI/gudhi-devel
Project-URL: License, https://gudhi.inria.fr/licensing/
Platform: UNKNOWN
Requires-Python: >=3.8.0
Requires-Dist: numpy>=1.15.0
